chainql-0.4.7b4.dist-info/METADATA
chainql-0.4.7b4.dist-info/WHEEL
chainql/hex/__init__.pyi
chainql/hash/__init__.pyi
chainql/__init__.py
chainql/address/__init__.pyi
chainql/py.typed
chainql/chainql.pyi
chainql/ethereum/__init__.pyi
chainql/chainql.abi3.so
chainql-0.4.7b4.dist-info/RECORD
